MANIFEST.in
README.rst
VERSION.txt
setup.cfg
setup.py
pyclamdplus/__init__.py
pyclamdplus/exc.py
pyclamdplus.egg-info/PKG-INFO
pyclamdplus.egg-info/SOURCES.txt
pyclamdplus.egg-info/dependency_links.txt
pyclamdplus.egg-info/not-zip-safe
pyclamdplus.egg-info/requires.txt
pyclamdplus.egg-info/top_level.txt