Metadata-Version: 1.1
Name: pyclamdplus
Version: 1.1b2
Summary: Pythonic interface to the Clamav daemon
Home-page: UNKNOWN
Author: 2degrees Limited
Author-email: 2degrees-floss@googlegroups.com
License: GNU GPL v2 or later (http://www.gnu.org/licenses/gpl-2.0.html)
Keywords: clamav clamd pyclamav pyclamd antivirus anti-virus virus
Platform: UNKNOWN
Classifier: Development Status :: 4 - Beta
Classifier: Intended Audience :: Developers
Classifier: License :: OSI Approved :: GNU General Public License (GPL)
Classifier: Natural Language :: English
Classifier: Operating System :: OS Independent
Classifier: Programming Language :: Python :: 2
Classifier: Programming Language :: Python :: 3
Classifier: Topic :: Security
